packit_deploy/__about__.py
packit_deploy/__init__.py
packit_deploy/cli.py
packit_deploy/config.py
packit_deploy/docker_helpers.py
packit_deploy/packit_constellation.py
packit_deploy/py.typed
packit_deploy/templates/index.html.j2
packit_deploy/templates/nginx.conf.j2
packit_deploy-0.1.6.dist-info/METADATA
packit_deploy-0.1.6.dist-info/WHEEL
packit_deploy-0.1.6.dist-info/entry_points.txt
packit_deploy-0.1.6.dist-info/licenses/LICENSE.txt
packit_deploy-0.1.6.dist-info/RECORD
