Metadata-Version: 2.4
Name: packit-deploy
Version: 0.1.6
Project-URL: Documentation, https://github.com/mrc-ide/packit-deploy#readme
Project-URL: Issues, https://github.com/mrc-ide/packit-deploy/issues
Project-URL: Source, https://github.com/mrc-ide/packit-deploy
Author-email: Alex Hill <alex.hill@gmail.com>
License-Expression: MIT
License-File: LICENSE.txt
Classifier: Development Status :: 4 - Beta
Classifier: Programming Language :: Python
Classifier: Programming Language :: Python :: 3.9
Classifier: Programming Language :: Python :: 3.10
Classifier: Programming Language :: Python :: 3.11
Classifier: Programming Language :: Python :: 3.12
Classifier: Programming Language :: Python :: 3.13
Classifier: Programming Language :: Python :: Implementation :: CPython
Classifier: Programming Language :: Python :: Implementation :: PyPy
Requires-Python: >=3.9
Requires-Dist: click
Requires-Dist: constellation~=1.5.0
Requires-Dist: docker
Requires-Dist: jinja2
